zooz_cli/__init__.py
zooz_cli/cli.py
zooz_cli-1.1.5.dist-info/licenses/LICENSE
zooz_cli-1.1.5.dist-info/METADATA
zooz_cli-1.1.5.dist-info/WHEEL
zooz_cli-1.1.5.dist-info/entry_points.txt
zooz_cli-1.1.5.dist-info/top_level.txt
zooz_cli-1.1.5.dist-info/RECORD
