Metadata-Version: 2.4
Name: zooz-cli
Version: 1.1.5
Summary: CLI tool for transferring Microsoft Power Pages sites between environments
Author-email: Zooz Tech <itzharm@zooz-tech.co.il>
License: MIT License
Project-URL: Homepage, https://github.com/zooz-tech/zooz-cli
Project-URL: Repository, https://github.com/zooz-tech/zooz-cli
Project-URL: Issues, https://github.com/zooz-tech/zooz-cli/issues
Keywords: power-pages,cli,microsoft,dynamics,transfer
Classifier: Development Status :: 5 - Production/Stable
Classifier: Intended Audience :: Developers
Classifier: License :: OSI Approved :: MIT License
Classifier: Operating System :: OS Independent
Classifier: Programming Language :: Python :: 3
Classifier: Programming Language :: Python :: 3.7
Classifier: Programming Language :: Python :: 3.8
Classifier: Programming Language :: Python :: 3.9
Classifier: Programming Language :: Python :: 3.10
Classifier: Programming Language :: Python :: 3.11
Classifier: Programming Language :: Python :: 3.12
Classifier: Topic :: Software Development :: Libraries :: Python Modules
Classifier: Topic :: Utilities
Requires-Python: >=3.7
License-File: LICENSE
Requires-Dist: PyYAML>=5.4.0
Dynamic: license-file
